<!DOCTYPE picking>
<Nebula3>
 <FrameShader>
 
  <!-- depth-stencil buffers -->
  <DeclareDepthStencilTarget format="D24S8" relHeight="1" relWidth="1" name="DefaultDepthBuffer"/>
  
  <!-- picking buffer -->
  <DeclareRenderTarget relWidth="1" relHeight="1" format="R32F" msaa="false" name="PickingBuffer" depthTarget="DefaultDepthBuffer"/>
  
  <!-- draw all pickable objects -->
  <Pass renderTarget="PickingBuffer" clearColor="0,0,0,0" clearDepth="1" name="Picking">
	<Batch batchGroup="Picking" sorting="None" lighting="None" type="Geometry"/>
	<Batch batchGroup="PickingInFront" sorting="None" lighting="None" type="Geometry"/>
  </Pass>
 </FrameShader>
</Nebula3>
